{
    "10": [
        {
            "64-QAM": {
                "slots": 1,
                "reach": 80
            }
        }
    ],
    "40": [
        {
            "64-QAM": {
                "slots": 1,
                "reach": 80
            }
        }
    ],
    "100": [
        {
            "64-QAM": {
                "slots": 2,
                "reach": 80
            }
        }
    ],
    "400": [
        {
            "64-QAM": {
                "slots": 6,
                "reach": 80
            }
        }
    ],
    "1000": [
        {
            "64-QAM": {
                "slots": 14,
                "reach": 80
            }
        }
    ]
}